naveeen/__init__.py
naveeen/naveeen.py
naveeen-0.0.1.dist-info/METADATA
naveeen-0.0.1.dist-info/WHEEL
naveeen-0.0.1.dist-info/licenses/LICENCE
naveeen-0.0.1.dist-info/RECORD
