Metadata-Version: 2.1
Name: naveeen
Version: 0.0.1
Summary: See the difference, if you use threading and without.
Project-URL: Homepage, https://github.com/navawspy/mod
Project-URL: Bug Tracker, https://github.com/navawspy/mod
Author-email: naveen v <navpypi@gmail.com>
License-File: LICENCE
Classifier: License :: OSI Approved :: MIT License
Classifier: Operating System :: OS Independent
Classifier: Programming Language :: Python :: 3
Requires-Python: >=3.7
